build/lib/build/lib/docs/source/conf.py
build/lib/build/lib/yarsync/__init__.py
build/lib/build/lib/yarsync/version.py
build/lib/build/lib/yarsync/yarsync.py
build/lib/docs/source/conf.py
build/lib/yarsync/__init__.py
build/lib/yarsync/version.py
build/lib/yarsync/yarsync.py
docs/source/conf.py
yarsync/__init__.py
yarsync/version.py
yarsync/yarsync.py
yarsync-0.3.dist-info/licenses/LICENSE
yarsync-0.3.dist-info/METADATA
yarsync-0.3.dist-info/WHEEL
yarsync-0.3.dist-info/entry_points.txt
yarsync-0.3.dist-info/top_level.txt
yarsync-0.3.dist-info/RECORD
