Metadata-Version: 2.4
Name: yarsync
Version: 0.3
Summary: Yet Another Rsync is a file synchronization and backup tool
Home-page: https://github.com/ynikitenko/yarsync
Author: Yaroslav Nikitenko
Author-email: Yaroslav Nikitenko <metst13@gmail.com>
License-Expression: GPL-3.0
Project-URL: Documentation, https://yarsync.readthedocs.io
Project-URL: Source, https://github.com/ynikitenko/yarsync
Project-URL: Tracker, https://github.com/ynikitenko/yarsync/issues
Keywords: distributed,file,synchronization,rsync,backup
Classifier: Development Status :: 5 - Production/Stable
Classifier: Environment :: Console
Classifier: Intended Audience :: End Users/Desktop
Classifier: Intended Audience :: System Administrators
Classifier: Operating System :: POSIX :: Linux
Classifier: Programming Language :: Python :: 3 :: Only
Classifier: Programming Language :: Python :: 3.6
Classifier: Programming Language :: Python :: 3.7
Classifier: Programming Language :: Python :: 3.8
Classifier: Programming Language :: Python :: 3.9
Classifier: Programming Language :: Python :: 3.10
Classifier: Programming Language :: Python :: 3.11
Classifier: Programming Language :: Python :: 3.12
Classifier: Programming Language :: Python :: 3.13
Classifier: Programming Language :: Python :: Implementation :: CPython
Classifier: Programming Language :: Python :: Implementation :: PyPy
Classifier: Topic :: System :: Archiving
Classifier: Topic :: System :: Archiving :: Backup
Classifier: Topic :: System :: Archiving :: Mirroring
Classifier: Topic :: Utilities
Requires-Python: >=3.6
License-File: LICENSE
Provides-Extra: documentation
Requires-Dist: furo; extra == "documentation"
Requires-Dist: myst-parser; extra == "documentation"
Requires-Dist: sphinx; extra == "documentation"
Dynamic: author
Dynamic: home-page
Dynamic: license-file
Dynamic: requires-python
